mcp_server_odoo/__init__.py
mcp_server_odoo/__main__.py
mcp_server_odoo/odoo_client.py
mcp_server_odoo/server.py
odoo_mcp_server-0.1.3.dist-info/METADATA
odoo_mcp_server-0.1.3.dist-info/WHEEL
odoo_mcp_server-0.1.3.dist-info/licenses/LICENSE
odoo_mcp_server-0.1.3.dist-info/RECORD
