Metadata-Version: 2.4
Name: odoo-mcp-server
Version: 0.1.3
Summary: MCP server for Odoo ERP integration - enables AI assistants to interact with Odoo
Project-URL: Homepage, https://github.com/vzeman/odoo-mcp-server
Project-URL: Bug Tracker, https://github.com/vzeman/odoo-mcp-server/issues
Project-URL: Documentation, https://github.com/vzeman/odoo-mcp-server#readme
Author-email: Viktor Zeman <vzeman@gmail.com>
License: MIT
License-File: LICENSE
Keywords: ai,assistant,erp,integration,mcp,odoo
Classifier: Development Status :: 4 - Beta
Classifier: Intended Audience :: Developers
Classifier: License :: OSI Approved :: MIT License
Classifier: Programming Language :: Python :: 3
Classifier: Programming Language :: Python :: 3.10
Classifier: Programming Language :: Python :: 3.11
Classifier: Programming Language :: Python :: 3.12
Classifier: Topic :: Office/Business :: Financial :: Accounting
Classifier: Topic :: Software Development :: Libraries :: Python Modules
Requires-Python: >=3.10
Requires-Dist: httpx>=0.27.0
Requires-Dist: mcp>=1.0.0
Requires-Dist: pydantic>=2.0.0
Requires-Dist: python-dotenv>=1.0.0
Provides-Extra: dev
Requires-Dist: mypy>=1.0.0; extra == 'dev'
Requires-Dist: pytest-asyncio>=0.21.0; extra == 'dev'
Requires-Dist: pytest-cov>=4.0.0; extra == 'dev'
Requires-Dist: pytest>=8.0.0; extra == 'dev'
Requires-Dist: ruff>=0.1.0; extra == 'dev'
